{
  "version": "1.0",
  "last_updated": "2025-11-17T22:03:46.245922Z",
  "scores": [
    {
      "pr": "2",
      "score": -8,
      "breakdown": {
        "tests": 0,
        "bug_fix": 0,
        "docs": 1,
        "performance": 0,
        "security": -3,
        "penalties": -6
      },
      "timestamp": "2025-11-17T22:03:22.142881Z",
      "rubric_version": "unknown",
      "author": null,
      "files_changed": 0,
      "coverage_delta": null,
      "file_scores": {
        ".cursor/config/auto_pr_config.yaml": {
          "score": 0,
          "breakdown": {
            "tests": 0,
            "bug_fix": 0,
            "docs": 0,
            "performance": 0,
            "security": 0,
            "penalties": 0
          },
          "notes": "File: .cursor/config/auto_pr_config.yaml (no contributions)"
        },
        "README.md": {
          "score": 1,
          "breakdown": {
            "tests": 0,
            "bug_fix": 0,
            "docs": 1,
            "performance": 0,
            "security": 0,
            "penalties": 0
          },
          "notes": "File: README.md\nDocs: Documentation updated"
        },
        "README_AUTO_PR.md": {
          "score": 1,
          "breakdown": {
            "tests": 0,
            "bug_fix": 0,
            "docs": 1,
            "performance": 0,
            "security": 0,
            "penalties": 0
          },
          "notes": "File: README_AUTO_PR.md\nDocs: Documentation updated"
        },
        "docs/planning/AUTOMATED_PR_CREATION_STRATEGY.md": {
          "score": 1,
          "breakdown": {
            "tests": 0,
            "bug_fix": 0,
            "docs": 1,
            "performance": 0,
            "security": 0,
            "penalties": 0
          },
          "notes": "File: docs/planning/AUTOMATED_PR_CREATION_STRATEGY.md\nDocs: Documentation updated"
        },
        "docs/planning/AUTO_PR_IMPLEMENTATION_AUDIT.md": {
          "score": 1,
          "breakdown": {
            "tests": 0,
            "bug_fix": 0,
            "docs": 1,
            "performance": 0,
            "security": 0,
            "penalties": 0
          },
          "notes": "File: docs/planning/AUTO_PR_IMPLEMENTATION_AUDIT.md\nDocs: Documentation updated with engineering decisions"
        },
        "docs/planning/AUTO_PR_IMPLEMENTATION_COMPLETE.md": {
          "score": 1,
          "breakdown": {
            "tests": 0,
            "bug_fix": 0,
            "docs": 1,
            "performance": 0,
            "security": 0,
            "penalties": 0
          },
          "notes": "File: docs/planning/AUTO_PR_IMPLEMENTATION_COMPLETE.md\nDocs: Documentation updated"
        },
        "docs/planning/AUTO_PR_IMPLEMENTATION_SUMMARY.md": {
          "score": 1,
          "breakdown": {
            "tests": 0,
            "bug_fix": 0,
            "docs": 1,
            "performance": 0,
            "security": 0,
            "penalties": 0
          },
          "notes": "File: docs/planning/AUTO_PR_IMPLEMENTATION_SUMMARY.md\nDocs: Documentation updated"
        },
        "docs/planning/AUTO_PR_POST_IMPLEMENTATION_AUDIT_FINAL.md": {
          "score": 1,
          "breakdown": {
            "tests": 0,
            "bug_fix": 0,
            "docs": 1,
            "performance": 0,
            "security": 0,
            "penalties": 0
          },
          "notes": "File: docs/planning/AUTO_PR_POST_IMPLEMENTATION_AUDIT_FINAL.md\nDocs: Documentation updated with engineering decisions"
        },
        "docs/planning/AUTO_PR_USAGE_GUIDE.md": {
          "score": 1,
          "breakdown": {
            "tests": 0,
            "bug_fix": 0,
            "docs": 1,
            "performance": 0,
            "security": 0,
            "penalties": 0
          },
          "notes": "File: docs/planning/AUTO_PR_USAGE_GUIDE.md\nDocs: Documentation updated"
        },
        "docs/planning/DASHBOARD_UPDATE_RESOLUTION.md": {
          "score": 1,
          "breakdown": {
            "tests": 0,
            "bug_fix": 0,
            "docs": 1,
            "performance": 0,
            "security": 0,
            "penalties": 0
          },
          "notes": "File: docs/planning/DASHBOARD_UPDATE_RESOLUTION.md\nDocs: Documentation updated"
        },
        "docs/planning/FILE_LEVEL_SCORING_IMPLEMENTATION.md": {
          "score": 1,
          "breakdown": {
            "tests": 0,
            "bug_fix": 0,
            "docs": 1,
            "performance": 0,
            "security": 0,
            "penalties": 0
          },
          "notes": "File: docs/planning/FILE_LEVEL_SCORING_IMPLEMENTATION.md\nDocs: Documentation updated"
        },
        "docs/planning/INVESTIGATION_SUMMARY.md": {
          "score": 1,
          "breakdown": {
            "tests": 0,
            "bug_fix": 0,
            "docs": 1,
            "performance": 0,
            "security": 0,
            "penalties": 0
          },
          "notes": "File: docs/planning/INVESTIGATION_SUMMARY.md\nDocs: Documentation updated"
        },
        "docs/planning/PR_MERGE_SUCCESS.md": {
          "score": 1,
          "breakdown": {
            "tests": 0,
            "bug_fix": 0,
            "docs": 1,
            "performance": 0,
            "security": 0,
            "penalties": 0
          },
          "notes": "File: docs/planning/PR_MERGE_SUCCESS.md\nDocs: Documentation updated"
        },
        "docs/planning/REWARD_SCORE_AUTOMATION_TRIGGER.md": {
          "score": 1,
          "breakdown": {
            "tests": 0,
            "bug_fix": 0,
            "docs": 1,
            "performance": 0,
            "security": 0,
            "penalties": 0
          },
          "notes": "File: docs/planning/REWARD_SCORE_AUTOMATION_TRIGGER.md\nDocs: Documentation updated"
        },
        "docs/planning/REWARD_SCORE_GRANULARITY_ANALYSIS.md": {
          "score": 1,
          "breakdown": {
            "tests": 0,
            "bug_fix": 0,
            "docs": 1,
            "performance": 0,
            "security": 0,
            "penalties": 0
          },
          "notes": "File: docs/planning/REWARD_SCORE_GRANULARITY_ANALYSIS.md\nDocs: Documentation updated"
        },
        "docs/planning/REWARD_SCORE_SYSTEM_STATUS.md": {
          "score": 1,
          "breakdown": {
            "tests": 0,
            "bug_fix": 0,
            "docs": 1,
            "performance": 0,
            "security": 0,
            "penalties": 0
          },
          "notes": "File: docs/planning/REWARD_SCORE_SYSTEM_STATUS.md\nDocs: Documentation updated"
        }
      }
    }
  ],
  "aggregates": {
    "total_prs": 1,
    "average_score": -8.0,
    "score_distribution": {
      "negative (<0)": 1
    },
    "trends": [
      {
        "period": "2025-W46",
        "average": -8.0,
        "count": 1
      }
    ],
    "category_performance": {
      "tests": {
        "average": 0.0,
        "total": 0,
        "count": 0
      },
      "bug_fix": {
        "average": 0.0,
        "total": 0,
        "count": 0
      },
      "docs": {
        "average": 1.0,
        "total": 1,
        "count": 1
      },
      "performance": {
        "average": 0.0,
        "total": 0,
        "count": 0
      },
      "security": {
        "average": -3.0,
        "total": -3,
        "count": 1
      },
      "penalties": {
        "average": -6.0,
        "total": -6,
        "count": 1
      }
    },
    "anti_patterns": [
      {
        "pr": "2",
        "score": -8,
        "timestamp": "2025-11-17T22:03:22.142881Z",
        "breakdown": {
          "tests": 0,
          "bug_fix": 0,
          "docs": 1,
          "performance": 0,
          "security": -3,
          "penalties": -6
        },
        "penalties": -6
      }
    ]
  }
}